setup.py
Audit/__init__.py
sunday_12.egg-info/PKG-INFO
sunday_12.egg-info/SOURCES.txt
sunday_12.egg-info/dependency_links.txt
sunday_12.egg-info/top_level.txt