Metadata-Version: 2.1
Name: sunday-12
Version: 0.1
Summary: A Docker and AWS utility package
Home-page: https://github.com/javatechy/dokr
Author: Akhilesh
Author-email: kafkaservice@gmail.com
License: UNKNOWN
Platform: UNKNOWN
Classifier: Programming Language :: Python :: 3
Classifier: License :: OSI Approved :: MIT License
Classifier: Operating System :: OS Independent
